<?xml version = '1.0' encoding = 'UTF-8'?>
<TableProxyOraclev11g class="oracle.dbtools.crest.model.design.storage.oracle.v11g.TableProxyOraclev11g" name="VGT" directorySegmentName="seg_0" id="4454C8F5-1038-2A57-EBC7-B037BF43AE98">
<createdBy>Adm</createdBy>
<createdTime>2025-05-27 12:50:33 UTC</createdTime>
<ownerDesignName>FireGuardian 360</ownerDesignName>
<logging>YES</logging>
<partitionedRowMovement>DISABLE</partitionedRowMovement>
<temporaryChanged>false</temporaryChanged>
<accessDriverType>oracle_loader</accessDriverType>
<rejectLimit></rejectLimit>
<columnProxies itemClass="oracle.dbtools.crest.model.design.storage.oracle.v12c.ColumnProxyOraclev12c">
<ColumnProxy name="NM_VGT_TIPO" id="12395108-C007-27CF-B122-480BD8E932B0">
<createdBy>Adm</createdBy>
<createdTime>2025-05-27 12:50:33 UTC</createdTime>
<ownerDesignName>FireGuardian 360</ownerDesignName>
</ColumnProxy>
<ColumnProxy name="ID_VGT_VGT" id="3EBA8367-3347-A50F-FF89-0B205E831C59">
<createdBy>Adm</createdBy>
<createdTime>2025-05-27 12:50:33 UTC</createdTime>
<ownerDesignName>FireGuardian 360</ownerDesignName>
<autoIncrementDDL>TRIGGER</autoIncrementDDL>
</ColumnProxy>
<ColumnProxy name="DS_VGT_DESC" id="D4AF5F22-FC0B-5B2F-B7F0-6C9740ED5C60">
<createdBy>Adm</createdBy>
<createdTime>2025-05-27 12:50:33 UTC</createdTime>
<ownerDesignName>FireGuardian 360</ownerDesignName>
</ColumnProxy>
<ColumnProxy name="PC_VGT_RISCO" id="F406FA93-92F4-4074-5D21-09BF300D71B4">
<createdBy>Adm</createdBy>
<createdTime>2025-05-27 12:50:33 UTC</createdTime>
<ownerDesignName>FireGuardian 360</ownerDesignName>
<defaultValue>0.00</defaultValue>
</ColumnProxy>
</columnProxies>
<primaryKeys>
<PrimaryKey class="oracle.dbtools.crest.model.design.storage.oracle.v10g.PKProxyOraclev10g" name="PK_VGT" id="1FE213BA-ED9A-0BFD-6020-14E8579A13FD">
<createdBy>Adm</createdBy>
<createdTime>2025-05-27 12:50:33 UTC</createdTime>
<ownerDesignName>FireGuardian 360</ownerDesignName>
<indexSort>SORTED</indexSort>
</PrimaryKey>
</primaryKeys>
</TableProxyOraclev11g>
