<?xml version = '1.0' encoding = 'UTF-8'?>
<TableProxyOraclev11g class="oracle.dbtools.crest.model.design.storage.oracle.v11g.TableProxyOraclev11g" name="CHAT_MESSAGE" directorySegmentName="seg_0" id="8234C3F8-E2EB-BAE7-8515-502F9B146CB0">
<createdBy>Adm</createdBy>
<createdTime>2025-05-27 12:35:04 UTC</createdTime>
<ownerDesignName>FireGuardian 360</ownerDesignName>
<logging>YES</logging>
<partitionedRowMovement>DISABLE</partitionedRowMovement>
<temporaryChanged>false</temporaryChanged>
<accessDriverType>oracle_loader</accessDriverType>
<rejectLimit></rejectLimit>
<columnProxies itemClass="oracle.dbtools.crest.model.design.storage.oracle.v12c.ColumnProxyOraclev12c">
<ColumnProxy name="DH_CMT_SENT_AT" id="1E425823-56CD-E4E3-5B4C-411EE23BE1BD">
<createdBy>Adm</createdBy>
<createdTime>2025-05-27 12:35:04 UTC</createdTime>
<ownerDesignName>FireGuardian 360</ownerDesignName>
</ColumnProxy>
<ColumnProxy name="TX_CMT_TEXT" id="314F8AFA-2319-EDA9-C3C6-00471EC61A81">
<createdBy>Adm</createdBy>
<createdTime>2025-05-27 12:35:04 UTC</createdTime>
<ownerDesignName>FireGuardian 360</ownerDesignName>
</ColumnProxy>
<ColumnProxy name="CHAT_SESSION_ID_CSS_SESSION" id="35A624A9-30F9-8575-682A-52142724FDD0">
<createdBy>Adm</createdBy>
<createdTime>2025-05-27 12:35:04 UTC</createdTime>
<ownerDesignName>FireGuardian 360</ownerDesignName>
</ColumnProxy>
<ColumnProxy name="ID_CMT_MESSAGE" id="893BD9B8-1898-D1DF-319B-1129295D821E">
<createdBy>Adm</createdBy>
<createdTime>2025-05-27 12:35:04 UTC</createdTime>
<ownerDesignName>FireGuardian 360</ownerDesignName>
</ColumnProxy>
<ColumnProxy name="TP_CMT_SENDER" id="DC7D1305-CA01-2150-F16A-50121C117DFC">
<createdBy>Adm</createdBy>
<createdTime>2025-05-27 12:35:04 UTC</createdTime>
<ownerDesignName>FireGuardian 360</ownerDesignName>
</ColumnProxy>
</columnProxies>
<foreignKeys>
<ForeignKey class="oracle.dbtools.crest.model.design.storage.oracle.v10g.FKProxyOraclev10g" name="CHAT_MESSAGE_CHAT_SESSION_FK" id="2D4EDA9E-82F8-41A6-29B5-B64CC0DC3979">
<createdBy>Adm</createdBy>
<createdTime>2025-05-27 12:35:04 UTC</createdTime>
<ownerDesignName>FireGuardian 360</ownerDesignName>
</ForeignKey>
</foreignKeys>
<primaryKeys>
<PrimaryKey class="oracle.dbtools.crest.model.design.storage.oracle.v10g.PKProxyOraclev10g" name="CHAT_MESSAGE_PK" id="00A8220B-C191-6EED-4177-D25FA4CDADD5">
<createdBy>Adm</createdBy>
<createdTime>2025-05-27 12:35:04 UTC</createdTime>
<ownerDesignName>FireGuardian 360</ownerDesignName>
<indexSort>SORTED</indexSort>
</PrimaryKey>
</primaryKeys>
</TableProxyOraclev11g>
